Metadata-Version: 1.0
Name: pws
Version: 0.12
Summary: The most secure password keeper ever
Home-page: https://bitbucket.org/mattc41190/pws
Author: Matthew Cale
Author-email: mattc41190@gmail.com
License: MIT
Platform: UNKNOWN
